{"api-examples.md":"HHSMtQaV","components_button.md":"CuzbRRwF","components_descriptions.md":"BYh4aPLJ","components_dialog.md":"B-Q0-gYg","components_file-upload.md":"BIYVSLVN","components_image-upload.md":"CdlK7X1z","components_table.md":"D2v-ayKO","contact-me_index.md":"BTwzPdSH","en_components_button.md":"BDL8QmTU","en_components_descriptions.md":"BL4aUOws","en_components_dialog.md":"CyCmUG9I","en_components_file-upload.md":"Cl1ZGMZm","en_components_image-upload.md":"BEcdPTSA","en_components_table.md":"D1TfJtpJ","en_guide_index.md":"BQO0_1df","en_guide_installation.md":"DdeesCNJ","en_guide_quickstart.md":"BWnFioJr","en_index.md":"Cj38nXow","guide_index.md":"CyXNAUd8","guide_installation.md":"DLKUtGrf","guide_quickstart.md":"BYO-2icQ","index.md":"C6qm3aZO","markdown-examples.md":"i1TBQbzz"}
